CHANGES.rst
CONTRIBUTORS.rst
MANIFEST.in
README.rst
setup.py
cpskin/__init__.py
cpskin.workflow.egg-info/PKG-INFO
cpskin.workflow.egg-info/SOURCES.txt
cpskin.workflow.egg-info/dependency_links.txt
cpskin.workflow.egg-info/not-zip-safe
cpskin.workflow.egg-info/requires.txt
cpskin.workflow.egg-info/top_level.txt
cpskin/workflow/__init__.py
cpskin/workflow/configure.zcml
cpskin/workflow/events.py
cpskin/workflow/interfaces.py
cpskin/workflow/permissions.py
cpskin/workflow/permissions.zcml
cpskin/workflow/setuphandlers.py
cpskin/workflow/style.css
cpskin/workflow/testing.py
cpskin/workflow/testing.zcml
cpskin/workflow/upgradehandlers.py
cpskin/workflow/profiles/default/browserlayer.xml
cpskin/workflow/profiles/default/cpskin.workflow-default.txt
cpskin/workflow/profiles/default/cssregistry.xml
cpskin/workflow/profiles/default/import_steps.xml
cpskin/workflow/profiles/default/metadata.xml
cpskin/workflow/profiles/default/rolemap.xml
cpskin/workflow/profiles/default/sharing.xml
cpskin/workflow/profiles/default/workflows.xml
cpskin/workflow/profiles/default/workflows/cpskin_collective_contact_workflow/definition.xml
cpskin/workflow/profiles/default/workflows/cpskin_moderation_workflow/definition.xml
cpskin/workflow/profiles/default/workflows/cpskin_workflow/definition.xml
cpskin/workflow/profiles/testing/metadata.xml
cpskin/workflow/profiles/uninstall/browserlayer.xml
cpskin/workflow/profiles/uninstall/cpskin.workflow-uninstall.txt
cpskin/workflow/profiles/uninstall/cssregistry.xml
cpskin/workflow/profiles/uninstall/import_steps.xml
cpskin/workflow/profiles/uninstall/workflows.xml
cpskin/workflow/profiles/uninstall/workflows/cpskin_collective_contact_workflow/definition.xml
cpskin/workflow/profiles/uninstall/workflows/cpskin_moderation_workflow/definition.xml
cpskin/workflow/profiles/uninstall/workflows/cpskin_readonly_workflow/definition.xml
cpskin/workflow/profiles/uninstall/workflows/cpskin_workflow/definition.xml
cpskin/workflow/tests/__init__.py
cpskin/workflow/tests/test_excludefromnav.py
cpskin/workflow/tests/test_navigation.py
cpskin/workflow/tests/test_profiles.py
cpskin/workflow/upgrades/to1/workflows.xml
